PyDynamicDomains-0.0.1.data/scripts/pydynamicdomains
pydynamicdomains/__init__.py
pydynamicdomains/pydynamicdomains.py
PyDynamicDomains-0.0.1.dist-info/METADATA
PyDynamicDomains-0.0.1.dist-info/WHEEL
PyDynamicDomains-0.0.1.dist-info/top_level.txt
PyDynamicDomains-0.0.1.dist-info/RECORD
