Metadata-Version: 2.1
Name: PyDynamicDomains
Version: 0.0.1
Summary: PyDynamicDomains - A Dynamic Domain Name System Record Updater for Google Domains
Home-page: https://github.com/drpresq/pydynamicdomains
Author: Impostor
Author-email: drpresq@gmail.com
Classifier: Development Status :: 3 - Alpha
Classifier: Intended Audience :: End Users/Desktop
Classifier: License :: Other/Proprietary License
Classifier: Operating System :: POSIX :: Linux
Classifier: Programming Language :: Python :: 3.8
Classifier: Programming Language :: Python :: 3.9
Classifier: Programming Language :: Python :: 3.10
Requires-Dist: requests >=2.31.0
Provides-Extra: dev
Requires-Dist: pytest >=7.3.0 ; extra == 'dev'
